relaxed/__init__.py
relaxed/infer.py
relaxed/metrics.py
relaxed/mle.py
relaxed/ops.py
relaxed/py.typed
relaxed/_compat/__init__.py
relaxed/_compat/typing.py
relaxed-0.4.0.dist-info/METADATA
relaxed-0.4.0.dist-info/WHEEL
relaxed-0.4.0.dist-info/licenses/LICENSE
relaxed-0.4.0.dist-info/RECORD
